xkits_thread/__init__.py
xkits_thread/attribute.py
xkits_thread/executor.py
xkits_thread/lock.py
xkits_thread/proc.py
xkits_thread/task.py
xkits_thread-0.2.1.dist-info/LICENSE
xkits_thread-0.2.1.dist-info/METADATA
xkits_thread-0.2.1.dist-info/WHEEL
xkits_thread-0.2.1.dist-info/top_level.txt
xkits_thread-0.2.1.dist-info/zip-safe
xkits_thread-0.2.1.dist-info/RECORD
