Metadata-Version: 2.1
Name: xkits-thread
Version: 0.2.1
Summary: Thread module
Home-page: https://github.com/bondbox/xthreads/
Author: Mingzhe Zou
Author-email: zoumingzhe@outlook.com
License: GPLv2
Project-URL: Source Code, https://github.com/bondbox/xthreads/
Project-URL: Bug Tracker, https://github.com/bondbox/xthreads/issues
Project-URL: Documentation, https://github.com/bondbox/xthreads/
Keywords: thread-pool,threads,thread,task
Platform: any
Classifier: Programming Language :: Python
Classifier: Programming Language :: Python :: 3
Requires-Python: >=3.8
License-File: LICENSE
Requires-Dist: xkits-lib >=0.4
Requires-Dist: psutil
